Workbook

Sheet Cómo usar
A1: Planilla de prospectos de Vidriera
A2: Relevado el 20/10/2026 con la búsqueda local de Google (cerrajerías, odontólogos y talleres de Palermo y alrededores) y una revisión de cada web como visitante.
A4: Qué completás vos (celdas amarillas en la hoja Prospectos)
A5: Estado: elegilo de la lista desplegable cada vez que avances.
A6: Fecha 1er contacto: escribila (dd/mm/aaaa). Los tres seguimientos se calculan solos y se pintan de rojo cuando vencen si el estado sigue en “Contactado”.
A7: Próximo paso y Notas: lo que hablaste y qué sigue.
A9: Qué se calcula solo
A10: Puntos y Prioridad: según la situación, las reseñas y el puntaje (la tabla está en la hoja Puntos y la podés cambiar).
A11: Resumen: cuántos prospectos hay por prioridad, rubro y estado, y tus tasas de respuesta y cierre.
A13: Antes de contactar a cada uno
A14: Los datos de Google cambian: confirmá teléfono, horario y si sigue sin web (columna “Cómo verificarlo”).
A15: Para “Web caída” y “Web lenta”, probalo desde tu celular con datos móviles: la revisión se hizo desde la red de la facultad.
... A22: Meta semanal: 25 contactos, 5 diagnósticos, 1 o 2 propuestas.

Sheet Prospectos
A1: # | B1: Prioridad | C1: Puntos | D1: Negocio | E1: Rubro | F1: Zona | G1: Dirección | H1: Teléfono | I1: Tipo de línea | J1: WhatsApp | K1: Puntaje Google | L1: Reseñas | M1: Horario (al relevar) | N1: Web actual | O1: Situación | P1: Problema detectado | Q1: Cómo verificarlo | R1: Gancho para el primer mensaje | S1: Pack sugerido | T1: Canal recomendado | U1: Guion a usar | V1: Demo a mostrar | W1: Estado | X1: Fecha 1er contacto | Y1: Seguimiento 1 (+3 días) | Z1: Seguimiento 2 (+7 días) | AA1: Último aviso (+14 días) | AB1: Próximo paso | AC1: Notas
A2: 1 | B2: =IF(C2>=5,"Alta",IF(C2>=3,"Media","Baja")) | C2: =IFERROR(VLOOKUP(O2,Puntos!$A$3:$B$12,2,FALSE),0)+IF(L2>=100,2,IF(L2>=30,1,0))+IF(K2>=4.5,1,0)-IF(K2<3,2,0) | D2: Cerrajería Herrería Punta Palermo | E2: Cerrajería | F2: Palermo | G2: Jerónimo Salguero 2128 | H2: 011 4478-8211 | I2: Fijo | J2: — | K2: 5 | L2: 227 | M2: Lun a sáb, cierra 19:30 h | N2: No tiene (solo publicaciones de Instagram en la ficha) | O2: Sin web | P2: Ficha de Google sin sitio web propio. | Q2: Buscalo en Google Maps: la ficha no tiene botón “Sitio web”. | R2: 227 reseñas de 5 estrellas y sin web: quien busca “cerrajero en Palermo” llega a la competencia que sí tiene página. | S2: Presencia (o Profesional) | T2: Visita presencial | U2: G1 Sin web | V2: Demo cerrajería | W2: Sin contactar | Y2: =IF(X2="","",X2+3) | Z2: =IF(X2="","",X2+7) | AA2: =IF(X2="","",X2+14)
A3: 2 | B3: =IF(C3>=5,"Alta",IF(C3>=3,"Media","Baja")) | C3: =IFERROR(VLOOKUP(O3,Puntos!$A$3:$B$12,2,FALSE),0)+IF(L3>=100,2,IF(L3>=30,1,0))+IF(K3>=4.5,1,0)-IF(K3<3,2,0) | D3: Cerrajería Santi | E3: Cerrajería | F3: Palermo | G3: Paraguay 3492 | H3: 011 4826-4313 | I3: Fijo | J3: — | K3: 4.7 | L3: 83 | M3: Cierra 18 h | N3: No tiene | O3: Sin web | P3: Ficha de Google sin sitio web. | Q3: Buscalo en Google Maps: la ficha no tiene botón “Sitio web”. | R3: Más de 10 años en el barrio y 83 reseñas: una página con servicios y copias de llaves le suma clientes de paso. | S3: Presencia (o Profesional) | T3: Visita presencial | U3: G1 Sin web | V3: Demo cerrajería | W3: Sin contactar | Y3: =IF(X3="","",X3+3) | Z3: =IF(X3="","",X3+7) | AA3: =IF(X3="","",X3+14)
A4: 3 | B4: =IF(C4>=5,"Alta",IF(C4>=3,"Media","Baja")) | C4: =IFERROR(VLOOKUP(O4,Puntos!$A$3:$B$12,2,FALSE),0)+IF(L4>=100,2,IF(L4>=30,1,0))+IF(K4>=4.5,1,0)-IF(K4<3,2,0) | D4: Cerrajería Keys 24 h | E4: Cerrajería | F4: Recoleta / Palermo | G4: Ecuador 1111 | H4: 011 15-2634-3514 | I4: Celular | J4: =HYPERLINK("https://wa.me/5491126343514","Abrir WhatsApp") | K4: 4.2 | L4: 123 | M4: 24 h | N4: No tiene | O4: Sin web | P4: Ficha de Google sin sitio web, aunque atiende urgencias 24 h. | Q4: Buscalo en Google Maps: la ficha no tiene botón “Sitio web”. | R4: Atiende las 24 horas y no tiene web: de noche la gente busca en el celular y llama al primero que muestra precio y botón de llamar. | S4: Presencia (o Profesional) | T4: WhatsApp + visita | U4: G1 Sin web | V4: Demo cerrajería | W4: Sin contactar | Y4: =IF(X4="","",X4+3) | Z4: =IF(X4="","",X4+7) | AA4: =IF(X4="","",X4+14)
A5: 4 | B5: =IF(C5>=5,"Alta",IF(C5>=3,"Media","Baja")) | C5: =IFERROR(VLOOKUP(O5,Puntos!$A$3:$B$12,2,FALSE),0)+IF(L5>=100,2,IF(L5>=30,1,0))+IF(K5>=4.5,1,0)-IF(K5<3,2,0) | D5: Antigua Cerrajería Norte | E5: Cerrajería | F5: Palermo | G5: Beruti 3611 | H5: 011 4831-9673 | I5: Fijo | J5: — | K5: 4.5 | L5: 70 | M5: Cierra 18 h | N5: No tiene | O5: Sin web | P5: Ficha de Google sin sitio web. | Q5: Buscalo en Google Maps: la ficha no tiene botón “Sitio web”. | R5: Más de 15 años de trayectoria y ninguna web que lo cuente. | S5: Presencia (o Profesional) | T5: Visita presencial | U5: G1 Sin web | V5: Demo cerrajería | W5: Sin contactar | Y5: =IF(X5="","",X5+3) | Z5: =IF(X5="","",X5+7) | AA5: =IF(X5="","",X5+14)
A6: 5 | B6: =IF(C6>=5,"Alta",IF(C6>=3,"Media","Baja")) | C6: =IFERROR(VLOOKUP(O6,Puntos!$A$3:$B$12,2,FALSE),0)+IF(L6>=100,2,IF(L6>=30,1,0))+IF(K6>=4.5,1,0)-IF(K6<3,2,0) | D6: Cerrajería Maciel | E6: Cerrajería | F6: Palermo (ver ficha) | G6: Ver ficha de Google | H6: 011 4829-0881 | I6: Fijo | J6: — | K6: 4.8 | L6: 32 | M6: Cierra 19 h | N6: No tiene | O6: Sin web | P6: Ficha de Google sin sitio web. | Q6: Buscalo en Google Maps: la ficha no tiene botón “Sitio web”. | R6: 4,8 estrellas y más de 10 años: falta solo la web para que lo encuentren fuera de la cuadra. | S6: Presencia (o Profesional) | T6: Visita presencial | U6: G1 Sin web | V6: Demo cerrajería | W6: Sin contactar | Y6: =IF(X6="","",X6+3) | Z6: =IF(X6="","",X6+7) | AA6: =IF(X6="","",X6+14)
A7: 6 | B7: =IF(C7>=5,"Alta",IF(C7>=3,"Media","Baja")) | C7: =IFERROR(VLOOKUP(O7,Puntos!$A$3:$B$12,2,FALSE),0)+IF(L7>=100,2,IF(L7>=30,1,0))+IF(K7>=4.5,1,0)-IF(K7<3,2,0) | D7: Cerrajería Buenos Aires | E7: Cerrajería | F7: Recoleta / Barrio Norte | G7: Av. Pueyrredón 1418 | H7: 011 15-4177-3899 | I7: Celular | J7: =HYPERLINK("https://wa.me/5491141773899","Abrir WhatsApp") | K7: 4.5 | L7: 25 | M7: 24 h | N7: No tiene | O7: Sin web | P7: Ficha de Google sin sitio web, atiende 24 h. | Q7: Buscalo en Google Maps: la ficha no tiene botón “Sitio web”. | R7: Urgencias 24 h sin web: una landing con botón de llamar y zonas de cobertura es justo lo que se busca a la madrugada. | S7: Presencia (o Profesional) | T7: WhatsApp + visita | U7: G1 Sin web | V7: Demo cerrajería | W7: Sin contactar | Y7: =IF(X7="","",X7+3) | Z7: =IF(X7="","",X7+7) | AA7: =IF(X7="","",X7+14)
A8: 7 | B8: =IF(C8>=5,"Alta",IF(C8>=3,"Media","Baja")) | C8: =IFERROR(VLOOKUP(O8,Puntos!$A$3:$B$12,2,FALSE),0)+IF(L8>=100,2,IF(L8>=30,1,0))+IF(K8>=4.5,1,0)-IF(K8<3,2,0) | D8: Cerrajería Santa Fe Emergencias 24 h | E8: Cerrajería | F8: Palermo / Barrio Norte | G8: Av. Santa Fe 3112, local 3 | H8: 011 4826-8656 | I8: Fijo | J8: — | K8: 3.9 | L8: 27 | M8: Cierra 20:30 h | N8: No tiene | O8: Sin web | P8: Ficha de Google sin sitio web. | Q8: Buscalo en Google Maps: la ficha no tiene botón “Sitio web”. | R8: Sobre Av. Santa Fe y con “emergencias” en el nombre, pero sin web donde mostrar precios y horarios. | S8: Presencia (o Profesional) | T8: Visita presencial | U8: G1 Sin web | V8: Demo cerrajería | W8: Sin contactar | Y8: =IF(X8="","",X8+3) | Z8: =IF(X8="","",X8+7) | AA8: =IF(X8="","",X8+14)
A9: 8 | B9: =IF(C9>=5,"Alta",IF(C9>=3,"Media","Baja")) | C9: =IFERROR(VLOOKUP(O9,Puntos!$A$3:$B$12,2,FALSE),0)+IF(L9>=100,2,IF(L9>=30,1,0))+IF(K9>=4.5,1,0)-IF(K9<3,2,0) | D9: Cerrajería Alfredo | E9: Cerrajería | F9: Palermo | G9: Paunero 2747 | H9: 011 3094-9611 | I9: Celular (probable) | J9: =HYPERLINK("https://wa.me/5491130949611","Abrir WhatsApp") | K9: 5 | L9: 9 | M9: Cierra 19 h | N9: No tiene | O9: Sin web | P9: Ficha de Google sin sitio web y pocas reseñas. | Q9: Buscalo en Google Maps: la ficha no tiene botón “Sitio web”. | R9: 5 estrellas con pocas reseñas: una web y un QR para pedir reseñas lo hacen crecer rápido. | S9: Presencia (o Profesional) | T9: WhatsApp + visita | U9: G1 Sin web | V9: Demo cerrajería | W9: Sin contactar | Y9: =IF(X9="","",X9+3) | Z9: =IF(X9="","",X9+7) | AA9: =IF(X9="","",X9+14)
A10: 9 | B10: =IF(C10>=5,"Alta",IF(C10>=3,"Media","Baja")) | C10: =IFERROR(VLOOKUP(O10,Puntos!$A$3:$B$12,2,FALSE),0)+IF(L10>=100,2,IF(L10>=30,1,0))+IF(K10>=4.5,1,0)-IF(K10<3,2,0) | D10: Cerrajería Mi Service | E10: Cerrajería | F10: Palermo (ver ficha) | G10: Ver ficha de Google | H10: 011 5501-7718 | I10: Fijo | J10: — | K10: 3 | L10: 8 | M10: Cierra 18:30 h | N10: No tiene | O10: Sin web | P10: Ficha de Google sin sitio web y categoría genérica (“Comercio”). | Q10: Buscalo en Google Maps: la ficha no tiene botón “Sitio web”. | R10: Su ficha ni siquiera dice que es cerrajería: web propia más ficha bien configurada. | S10: Presencia (o Profesional) | T10: Visita presencial | U10: G1 Sin web | V10: Demo cerrajería | W10: Sin contactar | Y10: =IF(X10="","",X10+3) | Z10: =IF(X10="","",X10+7) | AA10: =IF(X10="","",X10+14)
A11: 10 | B11: =IF(C11>=5,"Alta",IF(C11>=3,"Media","Baja")) | C11: =IFERROR(VLOOKUP(O11,Puntos!$A$3:$B$12,2,FALSE),0)+IF(L11>=100,2,IF(L11>=30,1,0))+IF(K11>=4.5,1,0)-IF(K11<3,2,0) | D11: Cerrajería Palermo (Bulnes) | E11: Cerrajería | F11: Palermo | G11: Bulnes 1854 | H11: 011 4823-9720 | I11: Fijo | J11: — | K11: 2.2 | L11: 13 | M11: Cierra 20 h | N11: No tiene | O11: Sin web | P11: Ficha sin sitio web y puntaje bajo (2,2). | Q11: Buscalo en Google Maps: la ficha no tiene botón “Sitio web”. | R11: Puntaje bajo: antes de la web le conviene un sistema de reseñas. Prioridad baja. | S11: Presencia (o Profesional) | T11: Visita presencial | U11: G1 Sin web | V11: Demo cerrajería | W11: Sin contactar | Y11: =IF(X11="","",X11+3) | Z11: =IF(X11="","",X11+7) | AA11: =IF(X11="","",X11+14)
A12: 11 | B12: =IF(C12>=5,"Alta",IF(C12>=3,"Media","Baja")) | C12: =IFERROR(VLOOKUP(O12,Puntos!$A$3:$B$12,2,FALSE),0)+IF(L12>=100,2,IF(L12>=30,1,0))+IF(K12>=4.5,1,0)-IF(K12<3,2,0) | D12: Cerrajería Romero | E12: Cerrajería | F12: Palermo | G12: Aráoz 2396 | H12: — | I12: Sin teléfono | J12: — | K12: 2.2 | L12: 18 | M12: Cierra 24 h | N12: No tiene | O12: Sin web | P12: Ficha sin sitio web, sin teléfono y puntaje bajo. | Q12: Buscalo en Google Maps: la ficha no tiene botón “Sitio web”. | R12: Ni siquiera tiene teléfono en Google: solo visita presencial. Prioridad baja. | S12: Presencia (o Profesional) | T12: Visita presencial | U12: G1 Sin web | V12: Demo cerrajería | W12: Sin contactar | Y12: =IF(X12="","",X12+3) | Z12: =IF(X12="","",X12+7) | AA12: =IF(X12="","",X12+14)
A13: 12 | B13: =IF(C13>=5,"Alta",IF(C13>=3,"Media","Baja")) | C13: =IFERROR(VLOOKUP(O13,Puntos!$A$3:$B$12,2,FALSE),0)+IF(L13>=100,2,IF(L13>=30,1,0))+IF(K13>=4.5,1,0)-IF(K13<3,2,0) | D13: Cerrajería Manu | E13: Cerrajería | F13: Palermo | G13: Av. Gral. Las Heras 3895 | H13: 011 3569-3218 | I13: Celular (probable) | J13: =HYPERLINK("https://wa.me/5491135693218","Abrir WhatsApp") | K13: 4.9 | L13: 54 | M13: 24 h | N13: Solo un link a WhatsApp | O13: Solo redes | P13: El “sitio web” de su ficha es un link de WhatsApp: no tiene página. | Q13: En la ficha de Google, el botón “Sitio web” lleva a una red social o a WhatsApp. | R13: Ya entendió que WhatsApp vende; una landing con ese mismo botón lo pone primero en Google. | S13: Presencia | T13: WhatsApp + visita | U13: G4 Solo redes | V13: Demo cerrajería | W13: Sin contactar | Y13: =IF(X13="","",X13+3) | Z13: =IF(X13="","",X13+7) | AA13: =IF(X13="","",X13+14)
A14: 13 | B14: =IF(C14>=5,"Alta",IF(C14>=3,"Media","Baja")) | C14: =IFERROR(VLOOKUP(O14,Puntos!$A$3:$B$12,2,FALSE),0)+IF(L14>=100,2,IF(L14>=30,1,0))+IF(K14>=4.5,1,0)-IF(K14<3,2,0) | D14: Cerrajería Sam-se | E14: Cerrajería | F14: Palermo | G14: Julián Álvarez 1417 | H14: 011 4832-5751 | I14: Fijo | J14: — | K14: 4.7 | L14: 110 | M14: Cierra 18 h | N14: Solo Facebook | O14: Solo redes | P14: El “sitio web” de su ficha es una página de Facebook. | Q14: En la ficha de Google, el botón “Sitio web” lleva a una red social o a WhatsApp. | R14: 110 reseñas y una página de Facebook como web: transmite menos confianza de la que se ganó. | S14: Presencia | T14: Visita presencial | U14: G4 Solo redes | V14: Demo cerrajería | W14: Sin contactar | Y14: =IF(X14="","",X14+3) | Z14: =IF(X14="","",X14+7) | AA14: =IF(X14="","",X14+14)
A15: 14 | B15: =IF(C15>=5,"Alta",IF(C15>=3,"Media","Baja")) | C15: =IFERROR(VLOOKUP(O15,Puntos!$A$3:$B$12,2,FALSE),0)+IF(L15>=100,2,IF(L15>=30,1,0))+IF(K15>=4.5,1,0)-IF(K15<3,2,0) | D15: Cerrajería Ezequiel | E15: Cerrajería | F15: Palermo | G15: Av. Raúl Scalabrini Ortiz 1607 | H15: 011 4833-9323 | I15: Fijo | J15: — | K15: 4.8 | L15: 40 | M15: Cierra 20 h | N15: Solo Instagram | O15: Solo redes | P15: El “sitio web” de su ficha es su Instagram. | Q15: En la ficha de Google, el botón “Sitio web” lleva a una red social o a WhatsApp. | R15: Instagram no aparece cuando buscan “cerrajero cerca”; la web sí. | S15: Presencia | T15: Visita presencial | U15: G4 Solo redes | V15: Demo cerrajería | W15: Sin contactar | Y15: =IF(X15="","",X15+3) | Z15: =IF(X15="","",X15+7) | AA15: =IF(X15="","",X15+14)
A16: 15 | B16: =IF(C16>=5,"Alta",IF(C16>=3,"Media","Baja")) | C16: =IFERROR(VLOOKUP(O16,Puntos!$A$3:$B$12,2,FALSE),0)+IF(L16>=100,2,IF(L16>=30,1,0))+IF(K16>=4.5,1,0)-IF(K16<3,2,0) | D16: Cerrajería del Auto Trevisani | E16: Cerrajería | F16: Palermo (ver ficha) | G16: José A. Cabrera 3876 | H16: 011 6368-0095 | I16: Celular (probable) | J16: =HYPERLINK("https://wa.me/5491163680095","Abrir WhatsApp") | K16: 4.9 | L16: 952 | M16: 24 h | N16: Tiene un link en Google (verificar) | O16: Verificar | P16: Tiene un link en la ficha pero no pude confirmar si es web propia o red social. | Q16: Abrí el link de su ficha de Google y anotá qué es. | R16: 952 reseñas: es un negocio grande. Revisá su web antes de contactar; si es vieja, va Pack Profesional. | S16: Según lo que encuentres | T16: WhatsApp + visita | U16: Revisar antes | V16: Demo cerrajería | W16: Sin contactar | Y16: =IF(X16="","",X16+3) | Z16: =IF(X16="","",X16+7) | AA16: =IF(X16="","",X16+14)
A17: 16 | B17: =IF(C17>=5,"Alta",IF(C17>=3,"Media","Baja")) | C17: =IFERROR(VLOOKUP(O17,Puntos!$A$3:$B$12,2,FALSE),0)+IF(L17>=100,2,IF(L17>=30,1,0))+IF(K17>=4.5,1,0)-IF(K17<3,2,0) | D17: Cerrajería Borges | E17: Cerrajería | F17: Palermo | G17: Jorge Luis Borges 2475 | H17: 011 7167-3377 | I17: Celular (probable) | J17: =HYPERLINK("https://wa.me/5491171673377","Abrir WhatsApp") | K17: 4.6 | L17: 91 | M17: 24 h | N17: Tiene un link en Google (verificar) | O17: Verificar | P17: Tiene un link en la ficha pero no pude confirmar si es web propia o red social. | Q17: Abrí el link de su ficha de Google y anotá qué es. | R17: Revisá el link de su ficha: si es Instagram o WhatsApp, es un prospecto ideal. | S17: Según lo que encuentres | T17: WhatsApp + visita | U17: Revisar antes | V17: Demo cerrajería | W17: Sin contactar | Y17: =IF(X17="","",X17+3) | Z17: =IF(X17="","",X17+7) | AA17: =IF(X17="","",X17+14)
A18: 17 | B18: =IF(C18>=5,"Alta",IF(C18>=3,"Media","Baja")) | C18: =IFERROR(VLOOKUP(O18,Puntos!$A$3:$B$12,2,FALSE),0)+IF(L18>=100,2,IF(L18>=30,1,0))+IF(K18>=4.5,1,0)-IF(K18<3,2,0) | D18: Consultorio Odontológico Dres. Gallo | E18: Odontología | F18: Palermo | G18: Jerónimo Salguero 2402 | H18: 011 6502-8364 | I18: Celular (probable) | J18: =HYPERLINK("https://wa.me/5491165028364","Abrir WhatsApp") | K18: 4.7 | L18: 230 | M18: Cierra 18 h | N18: No tiene | O18: Sin web | P18: Ficha de Google sin sitio web. | Q18: Buscalo en Google Maps: la ficha no tiene botón “Sitio web”. | R18: 230 reseñas y sin web: los pacientes nuevos que comparan consultorios no pueden ver tratamientos ni obras sociales. | S18: Presencia (o Profesional) | T18: WhatsApp + visita | U18: G1 Sin web | V18: Demo odontología | W18: Sin contactar | Y18: =IF(X18="","",X18+3) | Z18: =IF(X18="","",X18+7) | AA18: =IF(X18="","",X18+14)
A19: 18 | B19: =IF(C19>=5,"Alta",IF(C19>=3,"Media","Baja")) | C19: =IFERROR(VLOOKUP(O19,Puntos!$A$3:$B$12,2,FALSE),0)+IF(L19>=100,2,IF(L19>=30,1,0))+IF(K19>=4.5,1,0)-IF(K19<3,2,0) | D19: Odontología Dentaloffice | E19: Odontología | F19: Palermo | G19: Gurruchaga 2267 | H19: 011 2374-5336 | I19: Celular (probable) | J19: =HYPERLINK("https://wa.me/5491123745336","Abrir WhatsApp") | K19: 5 | L19: 124 | M19: Cierra 19:30 h | N19: No tiene | O19: Sin web | P19: Ficha de Google sin sitio web. | Q19: Buscalo en Google Maps: la ficha no tiene botón “Sitio web”. | R19: 124 reseñas de 5 estrellas: con una web y turnos por WhatsApp convierte esa reputación en pacientes. | S19: Presencia (o Profesional) | T19: WhatsApp + visita | U19: G1 Sin web | V19: Demo odontología | W19: Sin contactar | Y19: =IF(X19="","",X19+3) | Z19: =IF(X19="","",X19+7) | AA19: =IF(X19="","",X19+14)
A20: 19 | B20: =IF(C20>=5,"Alta",IF(C20>=3,"Media","Baja")) | C20: =IFERROR(VLOOKUP(O20,Puntos!$A$3:$B$12,2,FALSE),0)+IF(L20>=100,2,IF(L20>=30,1,0))+IF(K20>=4.5,1,0)-IF(K20<3,2,0) | D20: Palermo Dental (Güemes) | E20: Odontología | F20: Palermo | G20: Güemes 4474 | H20: 011 4946-0817 | I20: Fijo | J20: — | K20: 5 | L20: 51 | M20: Cierra 20 h | N20: No tiene | O20: Sin web | P20: Ficha de Google sin sitio web. | Q20: Buscalo en Google Maps: la ficha no tiene botón “Sitio web”. | R20: Mismo nombre que otros consultorios de la zona: sin web propia es fácil que lo confundan. | S20: Presencia (o Profesional) | T20: Visita presencial | U20: G1 Sin web | V20: Demo odontología | W20: Sin contactar | Y20: =IF(X20="","",X20+3) | Z20: =IF(X20="","",X20+7) | AA20: =IF(X20="","",X20+14)
A21: 20 | B21: =IF(C21>=5,"Alta",IF(C21>=3,"Media","Baja")) | C21: =IFERROR(VLOOKUP(O21,Puntos!$A$3:$B$12,2,FALSE),0)+IF(L21>=100,2,IF(L21>=30,1,0))+IF(K21>=4.5,1,0)-IF(K21<3,2,0) | D21: DLT Odontología | E21: Odontología | F21: Palermo | G21: Soler 3644 | H21: 011 15-2391-9556 | I21: Celular | J21: =HYPERLINK("https://wa.me/5491123919556","Abrir WhatsApp") | K21: 4.9 | L21: 312 | M21: Cierra 20 h | N21: Solo un link a WhatsApp | O21: Solo redes | P21: El “sitio web” de su ficha es un link de WhatsApp. | Q21: En la ficha de Google, el botón “Sitio web” lleva a una red social o a WhatsApp. | R21: 312 reseñas y ninguna página: con la demo del armador de turnos ve el salto enseguida. | S21: Presencia | T21: WhatsApp + visita | U21: G4 Solo redes | V21: Demo odontología | W21: Sin contactar | Y21: =IF(X21="","",X21+3) | Z21: =IF(X21="","",X21+7) | AA21: =IF(X21="","",X21+14)
A22: 21 | B22: =IF(C22>=5,"Alta",IF(C22>=3,"Media","Baja")) | C22: =IFERROR(VLOOKUP(O22,Puntos!$A$3:$B$12,2,FALSE),0)+IF(L22>=100,2,IF(L22>=30,1,0))+IF(K22>=4.5,1,0)-IF(K22<3,2,0) | D22: BYM Odontología | E22: Odontología | F22: Palermo | G22: Ortiz de Ocampo 2561 | H22: 011 7723-5061 | I22: Celular (probable) | J22: =HYPERLINK("https://wa.me/5491177235061","Abrir WhatsApp") | K22: 4.8 | L22: 67 | M22: Cierra 20:30 h | N22: Solo Instagram | O22: Solo redes | P22: El “sitio web” de su ficha es su Instagram. | Q22: En la ficha de Google, el botón “Sitio web” lleva a una red social o a WhatsApp. | R22: Hace implantes, ortodoncia y ATM: tratamientos caros que el paciente investiga en Google antes de decidir. | S22: Presencia | T22: WhatsApp + visita | U22: G4 Solo redes | V22: Demo odontología | W22: Sin contactar | Y22: =IF(X22="","",X22+3) | Z22: =IF(X22="","",X22+7) | AA22: =IF(X22="","",X22+14)
A23: 22 | B23: =IF(C23>=5,"Alta",IF(C23>=3,"Media","Baja")) | C23: =IFERROR(VLOOKUP(O23,Puntos!$A$3:$B$12,2,FALSE),0)+IF(L23>=100,2,IF(L23>=30,1,0))+IF(K23>=4.5,1,0)-IF(K23<3,2,0) | D23: Dental Palermo (Charcas) | E23: Odontología | F23: Palermo | G23: Charcas 3127 | H23: 011 3794-5890 | I23: Celular (probable) | J23: =HYPERLINK("https://wa.me/5491137945890","Abrir WhatsApp") | K23: 4.9 | L23: 234 | M23: Abre 8:30 h | N23: dentalpalermo.com.ar | O23: Web lenta | P23: La web tardó unos 26 segundos en cargar en la revisión del 20/10/2026. | Q23: Abrí la web en tu celular con datos móviles y cronometrá; probala en PageSpeed Insights. | R23: Una web que tarda 26 segundos pierde a casi todos los que entran desde el celular. | S23: Profesional (rehacer) | T23: WhatsApp + visita | U23: G3 Web lenta o caída | V23: Demo odontología | W23: Sin contactar | Y23: =IF(X23="","",X23+3) | Z23: =IF(X23="","",X23+7) | AA23: =IF(X23="","",X23+14)
A24: 23 | B24: =IF(C24>=5,"Alta",IF(C24>=3,"Media","Baja")) | C24: =IFERROR(VLOOKUP(O24,Puntos!$A$3:$B$12,2,FALSE),0)+IF(L24>=100,2,IF(L24>=30,1,0))+IF(K24>=4.5,1,0)-IF(K24<3,2,0) | D24: Malva Odontología | E24: Odontología | F24: Palermo | G24: Av. Cnel. Díaz 1737 | H24: 011 6111-2894 | I24: Celular (probable) | J24: =HYPERLINK("https://wa.me/5491161112894","Abrir WhatsApp") | K24: 5 | L24: 209 | M24: Cierra 18 h | N24: malvaodontologia.com.ar | O24: Web caída | P24: La web no cargó en la revisión del 20/10/2026 (verificalo desde otra red antes de contactar). | Q24: Abrila desde tu celular con datos móviles (no la red de la facultad). | R24: Si confirmás que no carga: 209 reseñas de 5 estrellas que mandan a una web caída. | S24: Rescate o Profesional | T24: WhatsApp + visita | U24: G3 Web lenta o caída | V24: Demo odontología | W24: Sin contactar | Y24: =IF(X24="","",X24+3) | Z24: =IF(X24="","",X24+7) | AA24: =IF(X24="","",X24+14)
A25: 24 | B25: =IF(C25>=5,"Alta",IF(C25>=3,"Media","Baja")) | C25: =IFERROR(VLOOKUP(O25,Puntos!$A$3:$B$12,2,FALSE),0)+IF(L25>=100,2,IF(L25>=30,1,0))+IF(K25>=4.5,1,0)-IF(K25<3,2,0) | D25: Urgencias Odontológicas Palermo | E25: Odontología | F25: Palermo | G25: Bonpland 1240 | H25: 011 5494-8595 | I25: Fijo | J25: — | K25: 4.2 | L25: 124 | M25: 24 h | N25: odontologiapalermo.com (Jimdo) | O25: Web básica | P25: Web armada con un constructor gratuito (Jimdo). | Q25: Mirá la web en el celular y en PageSpeed Insights. | R25: Atiende 24 h: una web rápida con botón de llamada y WhatsApp vale más que una plantilla genérica. | S25: Profesional | T25: Visita presencial | U25: G5 Web vieja | V25: Demo odontología | W25: Sin contactar | Y25: =IF(X25="","",X25+3) | Z25: =IF(X25="","",X25+7) | AA25: =IF(X25="","",X25+14)
A26: 25 | B26: =IF(C26>=5,"Alta",IF(C26>=3,"Media","Baja")) | C26: =IFERROR(VLOOKUP(O26,Puntos!$A$3:$B$12,2,FALSE),0)+IF(L26>=100,2,IF(L26>=30,1,0))+IF(K26>=4.5,1,0)-IF(K26<3,2,0) | D26: Dental Arcos | E26: Odontología | F26: Palermo | G26: Fitz Roy 1988 | H26: 011 15-3340-3962 | I26: Celular | J26: =HYPERLINK("https://wa.me/5491133403962","Abrir WhatsApp") | K26: 5 | L26: 75 | M26: Cierra 20 h | N26: dentalarcos.com.ar | O26: Sin HTTPS forzado | P26: La versión http no redirige a https: quien entra así ve “No seguro”. | Q26: Escribí la dirección con http:// y fijate si el navegador dice “No seguro”. | R26: Arreglo técnico chico: buena puerta de entrada para el plan de mantenimiento. | S26: Plan Esencial | T26: WhatsApp + visita | U26: G5 Web vieja | V26: Demo odontología | W26: Sin contactar | Y26: =IF(X26="","",X26+3) | Z26: =IF(X26="","",X26+7) | AA26: =IF(X26="","",X26+14)
A27: 26 | B27: =IF(C27>=5,"Alta",IF(C27>=3,"Media","Baja")) | C27: =IFERROR(VLOOKUP(O27,Puntos!$A$3:$B$12,2,FALSE),0)+IF(L27>=100,2,IF(L27>=30,1,0))+IF(K27>=4.5,1,0)-IF(K27<3,2,0) | D27: Palermo Dental Studio | E27: Odontología | F27: Palermo | G27: Rocamora 4343 | H27: 011 5420-2735 | I27: Fijo | J27: — | K27: 5 | L27: 12 | M27: Cierra 19 h | N27: palermodentalok.com.ar | O27: Sin HTTPS forzado | P27: La versión http no redirige a https. | Q27: Escribí la dirección con http:// y fijate si el navegador dice “No seguro”. | R27: Pocas reseñas: web ajustada más sistema de reseñas. | S27: Plan Esencial | T27: Visita presencial | U27: G5 Web vieja | V27: Demo odontología | W27: Sin contactar | Y27: =IF(X27="","",X27+3) | Z27: =IF(X27="","",X27+7) | AA27: =IF(X27="","",X27+14)
A28: 27 | B28: =IF(C28>=5,"Alta",IF(C28>=3,"Media","Baja")) | C28: =IFERROR(VLOOKUP(O28,Puntos!$A$3:$B$12,2,FALSE),0)+IF(L28>=100,2,IF(L28>=30,1,0))+IF(K28>=4.5,1,0)-IF(K28<3,2,0) | D28: Dental Soho | E28: Odontología | F28: Palermo Soho | G28: Gorriti 5399 | H28: 011 6574-8079 | I28: Celular (probable) | J28: =HYPERLINK("https://wa.me/5491165748079","Abrir WhatsApp") | K28: 4.8 | L28: 189 | M28: Cierra 20 h | N28: dentalsoho.com.ar | O28: Web desactualizada | P28: El pie de la web dice © 2024. | Q28: Mirá el año del pie de página. | R28: Detalle chico pero visible; ofrecé el plan de mantenimiento mensual. | S28: Plan Plus | T28: WhatsApp + visita | U28: G5 Web vieja | V28: Demo odontología | W28: Sin contactar | Y28: =IF(X28="","",X28+3) | Z28: =IF(X28="","",X28+7) | AA28: =IF(X28="","",X28+14)
A29: 28 | B29: =IF(C29>=5,"Alta",IF(C29>=3,"Media","Baja")) | C29: =IFERROR(VLOOKUP(O29,Puntos!$A$3:$B$12,2,FALSE),0)+IF(L29>=100,2,IF(L29>=30,1,0))+IF(K29>=4.5,1,0)-IF(K29<3,2,0) | D29: Taller Barceló | E29: Taller mecánico | F29: Palermo (ver ficha) | G29: Ver ficha de Google | H29: 011 4773-9172 | I29: Fijo | J29: — | K29: 4.9 | L29: 10 | M29: Cierra 18 h | N29: No tiene | O29: Sin web | P29: Ficha de Google sin sitio web. | Q29: Buscalo en Google Maps: la ficha no tiene botón “Sitio web”. | R29: Más de 10 años y 4,9 estrellas: una web con turnos y presupuesto previo lo diferencia. | S29: Presencia (o Profesional) | T29: Visita presencial | U29: G1 Sin web | V29: Demo cerrajería (adaptar) | W29: Sin contactar | Y29: =IF(X29="","",X29+3) | Z29: =IF(X29="","",X29+7) | AA29: =IF(X29="","",X29+14)
A30: 29 | B30: =IF(C30>=5,"Alta",IF(C30>=3,"Media","Baja")) | C30: =IFERROR(VLOOKUP(O30,Puntos!$A$3:$B$12,2,FALSE),0)+IF(L30>=100,2,IF(L30>=30,1,0))+IF(K30>=4.5,1,0)-IF(K30<3,2,0) | D30: Taller Palermo, primera calidad (chapa y pintura) | E30: Taller mecánico | F30: Palermo (ver ficha) | G30: Ver ficha de Google | H30: 011 15-2375-0509 | I30: Celular | J30: =HYPERLINK("https://wa.me/5491123750509","Abrir WhatsApp") | K30: 4.6 | L30: 46 | M30: Cierra 18 h | N30: No tiene | O30: Sin web | P30: Ficha de Google sin sitio web. | Q30: Buscalo en Google Maps: la ficha no tiene botón “Sitio web”. | R30: Más de 20 años en chapa y pintura: los trabajos de antes y después son ideales para una galería. | S30: Presencia (o Profesional) | T30: WhatsApp + visita | U30: G1 Sin web | V30: Demo cerrajería (adaptar) | W30: Sin contactar | Y30: =IF(X30="","",X30+3) | Z30: =IF(X30="","",X30+7) | AA30: =IF(X30="","",X30+14)
A31: 30 | B31: =IF(C31>=5,"Alta",IF(C31>=3,"Media","Baja")) | C31: =IFERROR(VLOOKUP(O31,Puntos!$A$3:$B$12,2,FALSE),0)+IF(L31>=100,2,IF(L31>=30,1,0))+IF(K31>=4.5,1,0)-IF(K31<3,2,0) | D31: Taller Palermo | E31: Taller mecánico | F31: Palermo (ver ficha) | G31: Ver ficha de Google | H31: 011 4426-9374 | I31: Fijo | J31: — | K31: 5 | L31: 6 | M31: Cierra 18 h | N31: No tiene | O31: Sin web | P31: Ficha de Google sin sitio web y pocas reseñas. | Q31: Buscalo en Google Maps: la ficha no tiene botón “Sitio web”. | R31: Web más un QR para pedir reseñas a cada cliente que retira el auto. | S31: Presencia (o Profesional) | T31: Visita presencial | U31: G1 Sin web | V31: Demo cerrajería (adaptar) | W31: Sin contactar | Y31: =IF(X31="","",X31+3) | Z31: =IF(X31="","",X31+7) | AA31: =IF(X31="","",X31+14)
A32: 31 | B32: =IF(C32>=5,"Alta",IF(C32>=3,"Media","Baja")) | C32: =IFERROR(VLOOKUP(O32,Puntos!$A$3:$B$12,2,FALSE),0)+IF(L32>=100,2,IF(L32>=30,1,0))+IF(K32>=4.5,1,0)-IF(K32<3,2,0) | D32: Taller posventa Palermo Motor | E32: Taller mecánico | F32: Palermo (ver ficha) | G32: Ver ficha de Google | H32: 011 15-2730-1339 | I32: Celular | J32: =HYPERLINK("https://wa.me/5491127301339","Abrir WhatsApp") | K32: 5 | L32: 9 | M32: Cierra 17 h | N32: No tiene | O32: Sin web | P32: Ficha de Google sin sitio web. | Q32: Buscalo en Google Maps: la ficha no tiene botón “Sitio web”. | R32: 5 estrellas con pocas reseñas: necesita que lo encuentren. | S32: Presencia (o Profesional) | T32: WhatsApp + visita | U32: G1 Sin web | V32: Demo cerrajería (adaptar) | W32: Sin contactar | Y32: =IF(X32="","",X32+3) | Z32: =IF(X32="","",X32+7) | AA32: =IF(X32="","",X32+14)
A33: 32 | B33: =IF(C33>=5,"Alta",IF(C33>=3,"Media","Baja")) | C33: =IFERROR(VLOOKUP(O33,Puntos!$A$3:$B$12,2,FALSE),0)+IF(L33>=100,2,IF(L33>=30,1,0))+IF(K33>=4.5,1,0)-IF(K33<3,2,0) | D33: El Campeón | E33: Taller mecánico | F33: Palermo (ver ficha) | G33: Ver ficha de Google | H33: 011 15-6207-9704 | I33: Celular | J33: =HYPERLINK("https://wa.me/5491162079704","Abrir WhatsApp") | K33: 4.7 | L33: 17 | M33: Cierra 20 h | N33: No tiene | O33: Sin web | P33: Ficha de Google sin sitio web. | Q33: Buscalo en Google Maps: la ficha no tiene botón “Sitio web”. | R33: El nombre no dice que es un taller: la web y la ficha tienen que decirlo claro. | S33: Presencia (o Profesional) | T33: WhatsApp + visita | U33: G1 Sin web | V33: Demo cerrajería (adaptar) | W33: Sin contactar | Y33: =IF(X33="","",X33+3) | Z33: =IF(X33="","",X33+7) | AA33: =IF(X33="","",X33+14)
A34: 33 | B34: =IF(C34>=5,"Alta",IF(C34>=3,"Media","Baja")) | C34: =IFERROR(VLOOKUP(O34,Puntos!$A$3:$B$12,2,FALSE),0)+IF(L34>=100,2,IF(L34>=30,1,0))+IF(K34>=4.5,1,0)-IF(K34<3,2,0) | D34: Gomería y Mecánica 24 h Palermo / Neumáticos Palermo | E34: Taller mecánico | F34: Palermo (ver ficha) | G34: Ver ficha de Google | H34: 011 2774-9223 | I34: Celular (probable) | J34: =HYPERLINK("https://wa.me/5491127749223","Abrir WhatsApp") | K34: 3.5 | L34: 193 | M34: Hasta la 1 h | N34: No tiene | O34: Sin web | P34: Dos fichas de Google con el mismo teléfono (193 y 84 reseñas) y ninguna web. | Q34: Buscalo en Google Maps: la ficha no tiene botón “Sitio web”. | R34: Dos fichas con el mismo teléfono: unificarlas y sumar una web ordena todo. | S34: Presencia (o Profesional) | T34: WhatsApp + visita | U34: G1 Sin web | V34: Demo cerrajería (adaptar) | W34: Sin contactar | Y34: =IF(X34="","",X34+3) | Z34: =IF(X34="","",X34+7) | AA34: =IF(X34="","",X34+14)
A35: 34 | B35: =IF(C35>=5,"Alta",IF(C35>=3,"Media","Baja")) | C35: =IFERROR(VLOOKUP(O35,Puntos!$A$3:$B$12,2,FALSE),0)+IF(L35>=100,2,IF(L35>=30,1,0))+IF(K35>=4.5,1,0)-IF(K35<3,2,0) | D35: Automeca (Villa Crespo) | E35: Taller mecánico | F35: Villa Crespo | G35: Ver ficha de Google | H35: 011 2171-4999 | I35: Celular (probable) | J35: =HYPERLINK("https://wa.me/5491121714999","Abrir WhatsApp") | K35: 5 | L35: 45 | M35: Cierra 18 h | N35: automeca.com.ar (WordPress 6.6) | O35: WordPress desactualizado | P35: La web usa WordPress 6.6.10, varias versiones atrás de la actual: más riesgo de hackeo. | Q35: Extensión Wappalyzer en el navegador, o “Ver código fuente” y buscá “generator”. | R35: Tiene web y la cuida: ofrecé actualización y plan de mantenimiento antes de que la hackeen. | S35: Rescate preventivo + Plan Esencial | T35: WhatsApp + visita | U35: G6 WordPress viejo | V35: Demo cerrajería (adaptar) | W35: Sin contactar | Y35: =IF(X35="","",X35+3) | Z35: =IF(X35="","",X35+7) | AA35: =IF(X35="","",X35+14)

Sheet Resumen
A1: Resumen de la prospección
A3: Prospectos en la planilla | B3: =COUNTA(Prospectos!D2:D235)
A4: Prioridad alta | B4: =COUNTIF(Prospectos!B2:B235,"Alta")
A5: Prioridad media | B5: =COUNTIF(Prospectos!B2:B235,"Media")
A6: Prioridad baja | B6: =COUNTIF(Prospectos!B2:B235,"Baja")
A8: Por rubro
A9: Cerrajería | B9: =COUNTIF(Prospectos!E2:E235,"Cerrajería")
A10: Odontología | B10: =COUNTIF(Prospectos!E2:E235,"Odontología")
A11: Taller mecánico | B11: =COUNTIF(Prospectos!E2:E235,"Taller mecánico")
A13: Embudo
A14: Sin contactar | B14: =COUNTIF(Prospectos!W2:W235,"Sin contactar")
A15: Contactado | B15: =COUNTIF(Prospectos!W2:W235,"Contactado")
A16: Respondió | B16: =COUNTIF(Prospectos!W2:W235,"Respondió")
A17: Diagnóstico agendado | B17: =COUNTIF(Prospectos!W2:W235,"Diagnóstico agendado")
A18: Propuesta enviada | B18: =COUNTIF(Prospectos!W2:W235,"Propuesta enviada")
A19: Ganado | B19: =COUNTIF(Prospectos!W2:W235,"Ganado")
A20: Perdido | B20: =COUNTIF(Prospectos!W2:W235,"Perdido")
A22: Tasa de respuesta (respondió o más / contactados) | B22: =IF((B15+B16+B17+B18+B19+B20)=0,0,(B16+B17+B18+B19)/(B15+B16+B17+B18+B19+B20))
A23: Tasa de cierre (ganados / contactados) | B23: =IF((B15+B16+B17+B18+B19+B20)=0,0,B19/(B15+B16+B17+B18+B19+B20))
A25: Metas del primer mes: 100 contactos, 15 diagnósticos, 3 a 5 clientes.

Sheet Puntos
A1: Puntos por situación (editables). Prioridad: 5 o más = Alta, 3 a 4 = Media, menos = Baja.
A2: Situación | B2: Puntos | C2: Por qué
A3: Sin web | B3: 3 | C3: El dolor más claro y la venta más fácil.
A4: Solo redes | B4: 3 | C4: Ya vende por redes: entiende el valor, le falta la web.
A5: Web caída | B5: 3 | C5: Urgente: está perdiendo clientes hoy.
A6: Web lenta | B6: 3 | C6: Urgente: casi nadie espera tanto.
A7: WordPress desactualizado | B7: 2 | C7: Riesgo de hackeo: venta de mantenimiento.
A8: Web básica | B8: 2 | C8: Hay web pero no convierte.
A9: Sin HTTPS forzado | B9: 1 | C9: Arreglo chico: entrada al plan mensual.
A10: Web desactualizada | B10: 1 | C10: Detalle visible, venta de mantenimiento.
A11: Verificar | B11: 1 | C11: Falta revisar el link de su ficha.
A12: Web OK | B12: 0 | C12: No es prioridad.
A14: Además: +2 si tiene 100 reseñas o más, +1 si tiene entre 30 y 99, +1 si su puntaje es 4,5 o más, −2 si es menor a 3.

Sheet Guiones
A1: Guiones (reemplazá lo que está entre corchetes; mandá primero el mensaje corto y la captura cuando respondan)
A2: Código | B2: Cuándo usarlo | C2: Mensaje
A3: G1 Sin web | B3: Negocio sin web (WhatsApp) | C3: Hola, ¿cómo estás? Soy Santiago, hago webs para [rubro] acá en Palermo. Vi que [Negocio] tiene [N] reseñas buenísimas en Google, pero no tiene página propia, así que quien te busca por primera vez no ve tus servicios ni un botón para escribirte. Te armé un boceto de cómo podría verse, ¿te lo mando por acá?
A4: G2 Visita | B4: Visita al local (cualquier caso) | C4: Hola, soy Santiago, trabajo acá en el barrio haciendo webs para negocios. No te vengo a vender nada ahora: te quería mostrar algo que vi de tu negocio en Google. ¿Tenés un minuto? [Mostrás la captura o la demo en el celular] ¿Cuántos clientes nuevos te llegan por Google hoy? Te dejo mi tarjeta con la demo; ¿te parece si el jueves te escribo y lo vemos con calma?
A5: G3 Web lenta o caída | B5: La web no carga o tarda mucho | C5: Hola, soy Santiago, desarrollador web en Buenos Aires. Quise entrar a la web de [Negocio] desde el celular y [no cargó / tardó más de 20 segundos]. Te aviso porque la mayoría de la gente se va antes de que termine de cargar. Si querés, la reviso sin cargo y te digo qué pasa y cuánto costaría resolverlo. ¿Te queda bien que te llame 10 minutos?
A6: G4 Solo redes | B6: Solo Instagram, Facebook o WhatsApp | C6: Hola, ¿cómo estás? Soy Santiago, hago webs para negocios de Palermo. Vi que en Google tu “sitio web” es tu [Instagram / Facebook / WhatsApp]. Funciona, pero cuando alguien busca “[rubro] en Palermo” no aparece y transmite menos confianza que una página propia. Te armé un boceto con el mismo botón de WhatsApp que ya usás, ¿te lo mando?
A7: G5 Web vieja | B7: Web desactualizada, sin HTTPS o muy básica | C7: Hola [Nombre], soy Santiago. Entré a la web de [Negocio] desde el celular y [el navegador la marca como “No segura” / el pie dice 2024 / se ve como una plantilla genérica]. Es un arreglo rápido y te puedo dejar todo actualizado y cuidado todos los meses. ¿Querés que te mande una captura de cómo se ve hoy y cómo quedaría?
A8: G6 WordPress viejo | B8: Web en WordPress desactualizado | C8: Hola [Nombre], soy Santiago, desarrollador web. Revisando webs de talleres de la zona vi que la de [Negocio] usa una versión vieja de WordPress. Las versiones viejas son las que más se hackean y terminan mostrando publicidad de casinos. Te la puedo actualizar y dejar protegida con un plan mensual. ¿Lo charlamos 10 minutos?
A9: S1 Seguimiento +3 días | B9: Si no respondió | C9: Hola [Nombre], ¿pudiste ver el boceto que te mandé?
A10: S2 Seguimiento +7 días | B10: Si sigue sin responder | C10: Te paso un dato: cuando alguien busca “[rubro] en Palermo”, los primeros resultados con web propia se llevan la mayoría de los llamados. Si querés lo vemos en 10 minutos.
A11: S3 Último aviso +14 días | B11: Cierre amable | C11: No te quiero llenar de mensajes. Si más adelante querés resolverlo, guardá mi número: Santiago, 11 3577-8063. ¡Éxitos con [Negocio]!
